setup.py
fxg2svg/__init__.py
fxg2svg/convert.py
fxg2svg/svgtarget.py
fxg2svg.egg-info/PKG-INFO
fxg2svg.egg-info/SOURCES.txt
fxg2svg.egg-info/dependency_links.txt
fxg2svg.egg-info/entry_points.txt
fxg2svg.egg-info/requires.txt
fxg2svg.egg-info/top_level.txt
fxg2svg/processors/__init__.py
fxg2svg/processors/common.py
fxg2svg/processors/default.py
fxg2svg/processors/fill.py
fxg2svg/processors/filters.py
fxg2svg/processors/geometry.py
fxg2svg/processors/img.py
fxg2svg/processors/mask.py
fxg2svg/processors/stroke.py
fxg2svg/processors/text.py
fxg2svg/tests/__init__.py
fxg2svg/utils/__init__.py
fxg2svg/utils/fonts.py