Metadata-Version: 1.1
Name: fxg2svg
Version: 0.1.5
Summary: FXG to SVG converter
Home-page: https://bitbucket.org/suhain/fxg2svg
Author: suhain
Author-email: suhain93@gmail.com
License: MIT
Platform: UNKNOWN
Classifier: b'Programming Language :: Python :: 3.4'
Classifier: b'Environment :: Console'
Classifier: b'Development Status :: 3 - Alpha'
Classifier: b'Intended Audience :: Developers'
Classifier: b'License :: OSI Approved :: MIT License'
